README.md
setup.py
cheesefactory_logger_postgres/__init__.py
cheesefactory_logger_postgres/connection.py
cheesefactory_logger_postgres/exceptions.py
cheesefactory_logger_postgres/model.py
cheesefactory_logger_postgres.egg-info/PKG-INFO
cheesefactory_logger_postgres.egg-info/SOURCES.txt
cheesefactory_logger_postgres.egg-info/dependency_links.txt
cheesefactory_logger_postgres.egg-info/requires.txt
cheesefactory_logger_postgres.egg-info/top_level.txt