Metadata-Version: 2.1
Name: cheesefactory-logger-postgres
Version: 0.1
Summary: An interface for logging to a PostgreSQL database.
Home-page: https://bitbucket.org/hellsgrannies/cheesefactory-logger-postgres
Author: Todd Salazar
Author-email: unixsal@yahoo.com
License: UNKNOWN
Keywords: cheesefactory logging logger log postgresql postgres development
Platform: UNKNOWN
Classifier: Development Status :: 4 - Beta
Classifier: Intended Audience :: Developers
Classifier: License :: OSI Approved :: BSD License
Classifier: Programming Language :: Python :: 3.6
Classifier: Programming Language :: Python :: 3.7
Classifier: Programming Language :: Python :: 3.8
Classifier: Programming Language :: Python :: 3.9
